mvgarch/__init__.py
mvgarch/mgarch.py
mvgarch/ugarch.py
mvgarch-1.2.4.dist-info/METADATA
mvgarch-1.2.4.dist-info/WHEEL
mvgarch-1.2.4.dist-info/licenses/LICENSE
mvgarch-1.2.4.dist-info/RECORD
