Metadata-Version: 2.3
Name: mvgarch
Version: 1.2.4
Summary: Multivariate GARCH modelling in Python
Project-URL: Homepage, https://github.com/jamesjtobin/mvgarch
Project-URL: Bug Tracker, https://github.com/jamesjtobin/mvgarch/issues
Author-email: Jack Tobin <tobjack330@gmail.com>
License: MIT License
License-File: LICENSE
Classifier: License :: OSI Approved :: MIT License
Classifier: Operating System :: POSIX :: Linux
Classifier: Programming Language :: Python :: 3
Requires-Python: >=3.10
Requires-Dist: arch
Requires-Dist: matplotlib
Requires-Dist: numpy
Requires-Dist: pandas
Requires-Dist: pmdarima
Requires-Dist: scipy
